eplus/__init__.py
eplus/appcfg_update.py
eplus/embed.py
eplus/environment.py
eplus/shell.py
eplus/utils.py
eplus-1.2.2.dist-info/METADATA
eplus-1.2.2.dist-info/WHEEL
eplus-1.2.2.dist-info/entry_points.txt
eplus-1.2.2.dist-info/top_level.txt
eplus-1.2.2.dist-info/RECORD
