Metadata-Version: 2.1
Name: eplus
Version: 1.2.2
Summary: Google App Engine extensions
Home-page: https://github.com/kulik0v/eplus
Author: WIX
Author-email: UNKNOWN
License: MIT
Download-URL: https://github.com/kulik0v/eplus/archive/master.zip
Platform: UNKNOWN
Classifier: Development Status :: 4 - Beta
Classifier: Intended Audience :: Developers
Classifier: License :: OSI Approved :: MIT License
Requires-Dist: PyYAML
